source_file/__init__.py
source_file/client.py
source_file/run.py
source_file/source.py
source_file/spec.json
source_file/utils.py
airbyte_source_file-0.6.0.dist-info/METADATA
airbyte_source_file-0.6.0.dist-info/WHEEL
airbyte_source_file-0.6.0.dist-info/entry_points.txt
airbyte_source_file-0.6.0.dist-info/RECORD
