Metadata-Version: 2.1
Name: airbyte-source-file
Version: 0.6.0
Summary: Source implementation for File
Home-page: https://airbyte.com
License: ELv2
Author: Airbyte
Author-email: contact@airbyte.io
Requires-Python: >=3.10,<3.12
Classifier: License :: Other/Proprietary License
Classifier: Programming Language :: Python :: 3
Classifier: Programming Language :: Python :: 3.10
Classifier: Programming Language :: Python :: 3.11
Requires-Dist: airbyte-cdk (>=7,<8)
Requires-Dist: beautifulsoup4 (==4.11.1)
Requires-Dist: boto3 (==1.21.21)
Requires-Dist: fastparquet (>=2024.2.0,<2025.0.0)
Requires-Dist: gcsfs (==2022.7.1)
Requires-Dist: genson (==1.3.0)
Requires-Dist: google-cloud-storage (==2.5.0)
Requires-Dist: html5lib (==1.1)
Requires-Dist: lxml (>=5.0,<6.0)
Requires-Dist: numpy (<2)
Requires-Dist: openpyxl (==3.1.0)
Requires-Dist: pandas (==2.2.3)
Requires-Dist: paramiko (==2.11.0)
Requires-Dist: pyarrow (==14.0.2)
Requires-Dist: pyxlsb (==1.0.10)
Requires-Dist: s3fs (==2022.7.1)
Requires-Dist: smart-open[all] (==0.6.0)
Requires-Dist: xlrd (==2.0.1)
Project-URL: Documentation, https://docs.airbyte.com/integrations/sources/file
Project-URL: Repository, https://github.com/airbytehq/airbyte
